ngSe/__init__.py
ngSe/browser.py
ngSe/by.py
ngSe/contract.py
ngSe/exceptions.py
ngSe/page.py
ngSe/utils.py
ngSe/VERSION
ngSe-0.1.11.dist-info/DESCRIPTION.rst
ngSe-0.1.11.dist-info/METADATA
ngSe-0.1.11.dist-info/metadata.json
ngSe-0.1.11.dist-info/RECORD
ngSe-0.1.11.dist-info/top_level.txt
ngSe-0.1.11.dist-info/WHEEL
