Metadata-Version: 2.0
Name: ngSe
Version: 0.1.11
Summary: A Selenium browser for javascript frameworks
Home-page: https://github.com/conslo/ngSe
Author: Travis Johnson
Author-email: travis@thisguy.codes
License: LGPLv2.1
Keywords: testing selenium browser chrome
Platform: UNKNOWN
Classifier: Development Status :: 3 - Alpha
Classifier: Intended Audience :: Developers
Classifier: Topic :: Software Development :: Testing
Classifier: License :: OSI Approved :: GNU Lesser General Public License v2 (LGPLv2)
Classifier: Programming Language :: Python :: 2
Classifier: Programming Language :: Python :: 2.7
Requires-Dist: selenium (>=2.44.0,<3)
